LICENSE
MANIFEST.in
NOTICE
README.md
init.py
requirements.txt
setup.py
carball/__init__.py
carball/command_line.py
carball/decompile_replays.py
carball/analysis/PROTOBUF_VERSION
carball/analysis/__init__.py
carball/analysis/analysis_manager.py
carball/analysis/cleaner/__init__.py
carball/analysis/cleaner/cleaner.py
carball/analysis/cleaner/frame_cleaner.py
carball/analysis/constants/__init__.py
carball/analysis/constants/basic_math.py
carball/analysis/constants/dropshot.py
carball/analysis/constants/field_constants.py
carball/analysis/constants/playlist.py
carball/analysis/events/__init__.py
carball/analysis/events/carry_detection.py
carball/analysis/events/event_creator.py
carball/analysis/events/boost_pad_detection/__init__.py
carball/analysis/events/boost_pad_detection/pickup_analysis.py
carball/analysis/events/bump_detection/__init__.py
carball/analysis/events/bump_detection/bump_analysis.py
carball/analysis/events/dropshot/__init__.py
carball/analysis/events/dropshot/ball.py
carball/analysis/events/dropshot/damage.py
carball/analysis/events/fifty_fifty/__init__.py
carball/analysis/events/fifty_fifty/fifty_analysis.py
carball/analysis/events/hit_detection/__init__.py
carball/analysis/events/hit_detection/base_hit.py
carball/analysis/events/hit_detection/hit_analysis.py
carball/analysis/events/hit_detection/hitbox/Vehicle Specifications v1.39 - Hitboxes, Handling.xlsx
carball/analysis/events/hit_detection/hitbox/__init__.py
carball/analysis/events/hit_detection/hitbox/car.py
carball/analysis/events/hit_detection/hitbox/hitbox.py
carball/analysis/events/hit_pressure/__init__.py
carball/analysis/events/hit_pressure/pressure_analysis.py
carball/analysis/events/kickoff_detection/__init__.py
carball/analysis/events/kickoff_detection/kickoff_analysis.py
carball/analysis/saltie_game/__init__.py
carball/analysis/saltie_game/saltie_game.py
carball/analysis/saltie_game/metadata/ApiDemo.py
carball/analysis/saltie_game/metadata/ApiGame.py
sprocket_carball.egg-info/PKG-INFO
sprocket_carball.egg-info/SOURCES.txt
sprocket_carball.egg-info/dependency_links.txt
sprocket_carball.egg-info/entry_points.txt
sprocket_carball.egg-info/requires.txt
sprocket_carball.egg-info/top_level.txt
