Metadata-Version: 2.4
Name: sprocket_carball
Version: 0.9.0
Summary: Rocket League replay parsing and analysis.
Home-page: https://github.com/SprocketBot/carball
Author: Sprocket Dev Team
Author-email: asaxplayinghorse@gmail.com
License: Apache 2.0
Keywords: rocket-league
License-File: LICENSE
License-File: NOTICE
Requires-Dist: pandas
Requires-Dist: protobuf==3.6.1
Requires-Dist: openpyxl
Requires-Dist: numpy
Requires-Dist: sprocket-boxcars-py
Dynamic: author
Dynamic: author-email
Dynamic: description
Dynamic: description-content-type
Dynamic: home-page
Dynamic: keywords
Dynamic: license
Dynamic: license-file
Dynamic: requires-dist
Dynamic: summary
